setup.py
xq_webapi/__init__.py
xq_webapi/api.py
xq_webapi/handler.py
xq_webapi/server.py
xq_webapi.egg-info/PKG-INFO
xq_webapi.egg-info/SOURCES.txt
xq_webapi.egg-info/dependency_links.txt
xq_webapi.egg-info/top_level.txt