Metadata-Version: 1.0
Name: xq-webapi
Version: 1.0.0.0
Summary: xq webapi
Home-page: UNKNOWN
Author: XQ
Author-email: 5273508@qq.com
License: MIT Licence
Keywords: pip,webapi
Platform: python 3.7
